whatsapplinkgen/__init__.py
whatsapplinkgen/core.py
whatsapplinkgen-0.1.dist-info/METADATA
whatsapplinkgen-0.1.dist-info/WHEEL
whatsapplinkgen-0.1.dist-info/top_level.txt
whatsapplinkgen-0.1.dist-info/RECORD
