Metadata-Version: 2.1
Name: whatsapplinkgen
Version: 0.1
Summary: An efficient utility for swiftly generating WhatsApp direct links from contact numbers stored in .csv files or Excel spreadsheets!
Author: Daivik Karbhari
Author-email: Daivik Karbhari <daivikkarbhari01@gmail.com>
Keywords: Whatsapp,whatsapp link genration,Link,Generation,Message without saving contacts,chat
Requires-Python: >=3
Requires-Dist: pandas
Requires-Dist: numpy
